sv_ttk/__init__.py
sv_ttk/py.typed
sv_ttk/sv.tcl
sv_ttk/theme/dark.tcl
sv_ttk/theme/light.tcl
sv_ttk/theme/sprites_dark.tcl
sv_ttk/theme/sprites_light.tcl
sv_ttk/theme/spritesheet_dark.png
sv_ttk/theme/spritesheet_light.png
sv_ttk-2.5.5.dist-info/LICENSE
sv_ttk-2.5.5.dist-info/METADATA
sv_ttk-2.5.5.dist-info/WHEEL
sv_ttk-2.5.5.dist-info/top_level.txt
sv_ttk-2.5.5.dist-info/RECORD
