Metadata-Version: 2.1
Name: sv_ttk
Version: 2.5.5
Summary: A gorgeous theme for Tkinter, based on Windows 11's UI
Home-page: https://github.com/rdbende/Sun-Valley-ttk-theme
Author: rdbende
Author-email: rdbende@proton.me
License: MIT
Project-URL: Source, https://github.com/rdbende/Sun-Valley-ttk-theme
Project-URL: Documentation, https://github.com/rdbende/Sun-Valley-ttk-theme/wiki
Project-URL: Tracker, https://github.com/rdbende/Sun-Valley-ttk-theme/issues
Keywords: sv-ttk,tcl,tcl/tk,theme,tile,tk,ttk,tkinter,modern,fluent,dark-theme,sun-valley,windows-11,winui
Platform: UNKNOWN
Classifier: Intended Audience :: Developers
Classifier: Topic :: Software Development :: User Interfaces
Classifier: Programming Language :: Python :: 3 :: Only
Classifier: Programming Language :: Python :: 3.7
Classifier: Programming Language :: Python :: 3.8
Classifier: Programming Language :: Python :: 3.9
Classifier: Programming Language :: Python :: 3.10
Classifier: Programming Language :: Python :: 3.11
Classifier: Programming Language :: Python :: 3.12
Classifier: Programming Language :: Tcl
Classifier: License :: OSI Approved :: MIT License
Classifier: Operating System :: OS Independent
Requires-Python: >=3.7
License-File: LICENSE
